{"id":"4","sigla":"AP","nome":"Amapá","cidades":[{"id":"203","nome":"Amapá","estado":"4"},{"id":"204","nome":"Calçoene","estado":"4"},{"id":"205","nome":"Cutias","estado":"4"},{"id":"206","nome":"Ferreira Gomes","estado":"4"},{"id":"207","nome":"Itaubal","estado":"4"},{"id":"208","nome":"Laranjal do Jari","estado":"4"},{"id":"209","nome":"Macapá","estado":"4"},{"id":"210","nome":"Mazagão","estado":"4"},{"id":"211","nome":"Oiapoque","estado":"4"},{"id":"212","nome":"Pedra Branca do Amaparí","estado":"4"},{"id":"213","nome":"Porto Grande","estado":"4"},{"id":"214","nome":"Pracuúba","estado":"4"},{"id":"215","nome":"Santana","estado":"4"},{"id":"216","nome":"Serra do Navio","estado":"4"},{"id":"217","nome":"Tartarugalzinho","estado":"4"},{"id":"218","nome":"Vitória do Jari","estado":"4"}]}